{"bascuspe_C2": {"FileList":["bascuspe0000.htm","bascuspeCATIAtoc.htm"],"TitleList":["DMU Space Engineering","TOC"],"WordList":{"beep":[1],"calculation":[1],"disconnect":[1],"select":[1],"triggered":[1],"sound":[1],"do":[1],"during":[1],"dmu":[1],"when":[1],"space":[1],"deactivate":[1],"mode":[1],"path":[1],"apache":[1],"xml":[1],"host":[1],"options":[1],"connection":[1],"if":[1],"results":[1],"connections":[1],"selected":[1],"you":[1],"which":[1],"using":[1],"manually":[1],"edit":[1],"in":[1],"need":[1],"want":[1],"specify":[1],"this":[1],"finished":[1],"is":[1],"check":[1],"engineering":[1],"list":[1],"click":[1],"field":[1],"left":[1],"port":[1],"deals":[1],"following":[1],"name":[1],"files":[1],"http":[1],"page":[1],"cleared":[1],"parameters":[1],"send":[1],"spy":[1],"browse":[1],"server":[1],"be":[1],"blank":[1],"hosting":[1],"automatically":[1],"clash":[1],"box":[1],"directory":[1],"catia":[1],"result":[1],"can":[1],"default":[1],"not":[1],"are":[1],"and":[1],"by":[1],"ends":[1],"now":[1],"of":[1],"disabled":[1],"where":[1],"clicking":[1],"drop-down":[1],"connect":[1],"established":[1],"set":[1],"assistant":[1],"clear":[1],"automatic":[1],"computation":[1],"the":[1],"toolbar":[1],"with":[1],"machine":[1],"stored":[1],"to":[1],"operation":[1]}}}